README.md
git_repo_backup/__init__.py
git_repo_backup/backup.py
git_repo_backup-2.0.0.dist-info/entry_points.txt
git_repo_backup-2.0.0.dist-info/WHEEL
git_repo_backup-2.0.0.dist-info/METADATA
git_repo_backup-2.0.0.dist-info/RECORD
